lib0308/__init__.py
lib0308/deck.py
lib0308/blackjack/__init__.py
lib0308/blackjack/game.py
lib0308/highlow/__init__.py
lib0308/highlow/game.py
tests/__init__.py
tests/test_blackjack_game.py
tests/test_deck.py
tests/test_highlow_game.py
lib0308-0.1.0.dist-info/LICENSE.txt
lib0308-0.1.0.dist-info/METADATA
lib0308-0.1.0.dist-info/WHEEL
lib0308-0.1.0.dist-info/top_level.txt
lib0308-0.1.0.dist-info/RECORD
